{"id":"0","models":[{"id":"eb6e4a5cdb8d4db996373661f958ad14","title":"办公楼2","type":"Building","size":[33.0328,13.2,18.4151],"version":"1"},{"id":"a63fbde906244f15a345954a10fa9adc","title":"定制1200深800宽机柜_（能开门）","type":"Placement","size":[0.8,2,1.2],"version":"6"},{"id":"20160718174742030112154","title":"海德森 配电柜1","type":"Placement","size":[0.8,2,0.6],"props":{"firm":"海德森","unittype":"配电柜1","loadbearing":"900","power":"1000","version":"1.0","devicetype":"独立设备","tags":"[\"配电柜\"]"},"version":"2"},{"id":"0003826aea654a14a6f393a0aa0db91a","title":"绿化带2","type":"WallPrefab","size":[1.2,0.64584,0.65],"version":"1"},{"id":"f3f991c7e3ad4d2f879fd19ea57c4832","title":"城市建筑_8","type":"Building","size":[58.9291,24.5993,34.5878],"version":"0"},{"id":"4EF86FC4FFA44013AC4F45E8CD0D343F","title":"枫树","type":"Placement","size":[5.66699,7.4,6.233],"version":"6"},{"id":"c26acc8a9f804d8da2f49aba46283ac3","title":"清风拂动的大树","type":"Placement","size":[7.85544,7.80654,7.44832],"version":"2"},{"id":"C3B70F51107C4ED7BC525A8B82D11E7A","title":"消防栓","type":"Placement","size":[0.21244,0.59222,0.18794],"version":"6"}],"textures":[{"id":"3OZVGE55PV0MY48FPRG5BELXKHV26NU5","ext":"jpg"},{"id":"UPEUIZIK19VMBPP9TLZJ3J3ILWK8V5ZB","ext":"jpg"},{"id":"IQR8PZE2SGEV2H07WX3EJK22CA6ZS0YG","ext":"jpg"},{"id":"81FDB96B43D441C5B3C650BFA2B76CD4","title":"白墙","type":"Texture","ext":"jpg","isDefault":true},{"id":"EB9ECFA1101C4A0ABB770ED3A9865441","ext":"jpg"},{"id":"gi4gwsw5az4zfw97ulhnft2knw2vn1um","title":"石路01","type":"Texture","ext":"jpg"}],"camInfo":{"eye":"-8.052183782509664 106.25502683219536 -7.20447165041689","target":"-8.052187666407365 2.660470592809336 -7.204368124084553"},"thingjsconfig":{"environment":"","environmentInside":"","isShowEnvMap":true},"buildings":[{"id":"7415404D-ED59-407D-AB57-08C5AACE07ED","properties":{"_styleTag_":"FacadeMain"},"position":[-280.27275760114964,236.01,250.0269944299219],"plans":[{"id":"B4BCC40E-BD03-454D-A060-5A138EC68419","userid":"主楼一层","name":"主楼一层","position":[-31.32881568488156,0,-26.162631965076393],"corners":[[33.226064734728716,0,38.449051150530906],[33.226064734728716,0,36.86285128659729],[33.226064734728716,0,-30.873028621720774],[-38.334275881011685,0,-30.873028635241127],[-38.334275881011685,0,38.449051150530906],[48.863498801485704,0,38.44905115950461],[48.863498801485704,0,-30.873028612747063]],"walls":[{"id":"7D824FE6-7675-464F-8EE1-CB4E90787F49","corners":[5,6],"type":0,"lefttexture":3,"righttexture":3,"edgetexture":4,"blocksize":[3,3],"uvmultiple":[1,1]},{"id":"1243C5F3-2710-4936-8D97-A52304296E97","corners":[3,4],"type":0,"lefttexture":3,"righttexture":3,"edgetexture":4,"blocksize":[3,3],"uvmultiple":[1,1]},{"id":"DC602657-5E5F-404B-B846-41601235F2A2","corners":[6,2],"type":0,"lefttexture":3,"righttexture":3,"edgetexture":4,"blocksize":[3,3],"uvmultiple":[1,1]},{"id":"7D5759DF-9F7B-4224-8852-59FFA168D48A","corners":[2,3],"type":0,"lefttexture":3,"righttexture":3,"edgetexture":4,"blocksize":[3,3],"uvmultiple":[1,1]},{"id":"2D51CCF6-C531-4D6B-875F-E479B47573C8","corners":[1,2],"type":0,"lefttexture":3,"righttexture":3,"edgetexture":4,"blocksize":[3,3],"uvmultiple":[1,1]},{"id":"E6CEEBD4-8E66-419A-9FDB-30E15853AED7","corners":[4,0],"type":0,"lefttexture":3,"righttexture":3,"edgetexture":4,"blocksize":[3,3],"uvmultiple":[1,1]},{"id":"D14C599D-C5BC-418E-B0F8-CB6B6B23E750","corners":[0,5],"type":0,"lefttexture":3,"righttexture":3,"edgetexture":4,"blocksize":[3,3],"uvmultiple":[1,1]},{"id":"D0880232-44B2-47CC-8A93-7A7B77E31D0C","corners":[1,0],"type":0,"lefttexture":3,"righttexture":3,"edgetexture":4,"blocksize":[3,3],"uvmultiple":[1,1]}],"rooms":[{"id":"4351CF8E-98FA-4FE4-A6EC-FB193346A4E7","userid":"房间01","name":"房间01","rooftexture":0,"ceilingtexture":1,"floortexture":2,"roofcustomtexture":0,"ceilingcustomtexture":1,"floorcustomtexture":2,"isshowroof":false,"isshowceiling":false,"corners":[0,1,2,3,4]},{"id":"DB51E066-59AE-4385-A050-43F30FC552FE","userid":"房间02","name":"房间02","rooftexture":0,"ceilingtexture":1,"floortexture":2,"roofcustomtexture":0,"ceilingcustomtexture":1,"floorcustomtexture":2,"corners":[1,0,5,6,2]}],"placements":[{"id":"5764B214-8613-4C4E-BEDB-DDC5F6DAB8F0","userid":"屏柜01","name":"屏柜01","properties":{"所属房间":"房间01","类型":"屏柜"},"position":[-253.82749240523592,241.01,250.04738575783648],"model":1,"_temp_belongroom":"房间01"},{"id":"8DFFA18F-86C2-47E4-BED5-E294127D58F9","userid":"屏柜02","name":"屏柜02","properties":{"所属房间":"房间01","类型":"屏柜"},"position":[-258.6055002642788,248.01,257.0413228252597],"model":1,"_temp_belongroom":"房间01"},{"id":"3DD948A8-20BF-4524-B757-3E173F28582C","userid":"屏柜03","name":"屏柜03","properties":{"所属房间":"房间01","类型":"屏柜"},"position":[-53.3835081233217,45.01,54.03525989268299],"model":1,"_temp_belongroom":"房间01"},{"id":"D514FAF1-5796-4818-A881-BF1DE519B0F6","userid":"屏柜04","name":"屏柜04","properties":{"所属房间":"房间01","类型":"屏柜"},"position":[-253.1615159823646,247.01,256.0291969601062],"model":1,"_temp_belongroom":"房间01"},{"id":"E2106931-BF11-4B2E-8AB6-1F5ABDDF78AB","userid":"屏柜05","name":"屏柜05","properties":{"所属房间":"房间01","类型":"屏柜"},"position":[-173.9395238414075,170.01,179.02313402752952],"model":1,"_temp_belongroom":"房间01"},{"id":"DB74709D-2B8B-4544-BF1D-80462A493797","userid":"屏柜06","name":"屏柜06","properties":{"所属房间":"房间01","类型":"屏柜"},"position":[-151.71753170045037,150.01,159.01707109495277],"model":1,"_temp_belongroom":"房间01"},{"id":"2D96B5FC-8231-43A7-8070-BC3BDA214A71","userid":"屏柜07","name":"屏柜07","properties":{"所属房间":"房间01","类型":"屏柜"},"position":[112.50446044050673,112.01,121.01100816237603],"model":1,"_temp_belongroom":"房间01"},{"id":"D13276AF-32FC-402C-BB9E-88DD0AF6BFF4","userid":"屏柜08","name":"屏柜08","properties":{"所属房间":"房间01","类型":"屏柜"},"position":[247.72645258146383,245.01,254.0049452297993],"model":1,"_temp_belongroom":"房间01"},{"id":"92FAA0A7-3A58-4D16-A875-1525F2288C4A","userid":"屏柜09","name":"屏柜09","properties":{"所属房间":"房间01","类型":"屏柜"},"position":[79.94844472242093,75.01,83.99888229722255],"model":1,"_temp_belongroom":"房间01"},{"id":"D6B939E9-5F68-40B1-8362-057AB2B90B12","userid":"屏柜10","name":"屏柜10","properties":{"所属房间":"房间01","类型":"屏柜"},"position":[26.170436863378043,19.01,27.992819364645808],"model":1,"_temp_belongroom":"房间01"},{"id":"B2398BF2-E65C-448B-B1BA-C465D24CB587","userid":"屏柜11","name":"屏柜11","properties":{"所属房间":"房间01","类型":"屏柜"},"position":[-146.82749240523592,134.01,139.50820924986598],"model":1,"_temp_belongroom":"房间01"},{"id":"16359F38-079B-4125-9077-21951BB9133E","userid":"屏柜12","name":"屏柜12","properties":{"所属房间":"房间01","类型":"屏柜"},"position":[-73.60550026427882,63.01,68.50214631728926],"model":1,"_temp_belongroom":"房间01"},{"id":"29013C51-2EC2-4A36-B2A9-D6FE4BB3206D","userid":"屏柜13","name":"屏柜13","properties":{"所属房间":"房间01","类型":"屏柜"},"position":[-116.3835081233217,108.01,113.49608338471252],"model":1,"_temp_belongroom":"房间01"},{"id":"7891E8CF-DE51-4645-91B7-5F022A0A5052","userid":"屏柜14","name":"屏柜14","properties":{"所属房间":"房间01","类型":"屏柜"},"position":[-89.16151598236459,83.01,88.49002045213578],"model":1,"_temp_belongroom":"房间01"},{"id":"389E33DD-870A-435C-9E52-DEAED7E2AD99","userid":"屏柜15","name":"屏柜15","properties":{"所属房间":"房间01","类型":"屏柜"},"position":[-155.9395238414075,152.01,157.48395751955903],"model":1,"_temp_belongroom":"房间01"},{"id":"F49A2CF0-5EEC-4469-9C9E-16B79050FD96","userid":"屏柜16","name":"屏柜16","properties":{"所属房间":"房间01","类型":"屏柜"},"position":[-152.7175317004504,151.01,156.4778945869823],"model":1,"_temp_belongroom":"房间01"},{"id":"7A8E914D-7E13-4AFD-A17A-B4E0CE89A9FA","userid":"屏柜17","name":"屏柜17","properties":{"所属房间":"房间01","类型":"屏柜"},"position":[251.5044604405067,251.01,256.47183165440555],"model":1,"_temp_belongroom":"房间01"},{"id":"D0644C88-B516-425A-A119-B16227E159AB","userid":"屏柜18","name":"屏柜18","properties":{"所属房间":"房间01","类型":"屏柜"},"position":[172.72645258146383,170.01,175.46576872182882],"model":1,"_temp_belongroom":"房间01"},{"id":"2FD003FD-018A-4D81-92E1-AAB6C41F02D5","userid":"屏柜19","name":"屏柜19","properties":{"所属房间":"房间01","类型":"屏柜"},"position":[216.94844472242093,212.01,217.45970578925207],"model":1,"_temp_belongroom":"房间01"},{"id":"D8D440DE-C462-4E2C-B7AE-66CE22F1BB73","userid":"屏柜20","name":"屏柜20","properties":{"所属房间":"房间01","类型":"屏柜"},"position":[121.17043686337803,114.01,119.45364285667533],"model":1,"_temp_belongroom":"房间01"},{"id":"CFE0EF5C-4432-4509-94CC-125F8BC44D13","userid":"屏柜21","name":"屏柜21","properties":{"所属房间":"房间01","类型":"屏柜"},"position":[-30.827492405235915,18.01,20.131577649035215],"model":1,"_temp_belongroom":"房间01"},{"id":"1E82C493-6B7D-4A75-867D-1E4551F63018","userid":"屏柜22","name":"屏柜22","properties":{"所属房间":"房间01","类型":"屏柜"},"position":[-35.6055002642788,25.01,27.125514716458476],"model":1,"_temp_belongroom":"房间01"},{"id":"ADABF67A-FE25-4C41-9AAB-6CF68BC426F1","userid":"屏柜23","name":"屏柜23","properties":{"所属房间":"房间01","类型":"屏柜"},"position":[-248.3835081233217,240.01,242.11945178388174],"model":1,"_temp_belongroom":"房间01"},{"id":"76F0D8DC-9D01-437C-9478-ACAA3FA5FE49","userid":"屏柜24","name":"屏柜24","properties":{"所属房间":"房间01","类型":"屏柜"},"position":[-78.16151598236459,72.01,74.11338885130499],"model":1,"_temp_belongroom":"房间01"},{"id":"A87B4557-210D-4F91-80A3-3E268DEC0FF0","userid":"屏柜25","name":"屏柜25","properties":{"所属房间":"房间01","类型":"屏柜"},"position":[-244.9395238414075,241.01,243.10732591872826],"model":1,"_temp_belongroom":"房间01"},{"id":"C31B97EE-F3A0-4911-B7E4-2484672A79A1","userid":"屏柜26","name":"屏柜26","properties":{"所属房间":"房间01","类型":"屏柜"},"position":[-161.71753170045037,160.01,162.1012629861515],"model":1,"_temp_belongroom":"房间01"},{"id":"0034DED1-E2B2-4892-9918-690F7410C3A7","userid":"屏柜27","name":"屏柜27","properties":{"所属房间":"房间01","类型":"屏柜"},"position":[166.50446044050673,166.01,168.09520005357479],"model":1,"_temp_belongroom":"房间01"},{"id":"AEA09DDC-7A88-4C1E-A94B-57367CB5F396","userid":"屏柜28","name":"屏柜28","properties":{"所属房间":"房间01","类型":"屏柜"},"position":[153.72645258146383,151.01,153.08913712099803],"model":1,"_temp_belongroom":"房间01"},{"id":"4D2F0059-717F-4BA0-A1A5-6029DFE77466","userid":"屏柜29","name":"屏柜29","properties":{"所属房间":"房间01","类型":"屏柜"},"position":[107.94844472242093,103.01,105.08307418842129],"model":1,"_temp_belongroom":"房间01"},{"id":"604D2925-5A5B-491E-B6E2-B9200BB6FF3B","userid":"屏柜30","name":"屏柜30","properties":{"所属房间":"房间01","类型":"屏柜"},"position":[65.17043686337804,58.01,60.07701125584455],"model":1,"_temp_belongroom":"房间01"},{"id":"559A456A-2767-4248-8DB4-4C657A8C7610","userid":"屏柜31","name":"屏柜31","properties":{"所属房间":"房间01","类型":"屏柜"},"position":[-29.827492405235915,17.01,-18.667329323926104],"model":1,"_temp_belongroom":"房间01"},{"id":"D1534784-9248-48A0-A665-76D77B199DC9","userid":"屏柜32","name":"屏柜32","properties":{"所属房间":"房间01","类型":"屏柜"},"position":[-210.6055002642788,200.01,-201.67339225650284],"model":1,"_temp_belongroom":"房间01"},{"id":"A3EEF721-5C65-4D79-B228-F641E9D06C4D","userid":"屏柜33","name":"屏柜33","properties":{"所属房间":"房间01","类型":"屏柜"},"position":[-84.38350812332169,76.01,-77.67945518907958],"model":1,"_temp_belongroom":"房间01"},{"id":"2D968254-8A39-41BE-92F4-13A3C7A8B37E","userid":"屏柜34","name":"屏柜34","properties":{"所属房间":"房间01","类型":"屏柜"},"position":[-133.1615159823646,127.01,-128.68551812165632],"model":1,"_temp_belongroom":"房间01"},{"id":"6AEEA1A8-05AB-4BD2-9711-A1B11B115DED","userid":"屏柜35","name":"屏柜35","properties":{"所属房间":"房间01","类型":"屏柜"},"position":[-239.9395238414075,236.01,-237.69158105423307],"model":1,"_temp_belongroom":"房间01"},{"id":"B0BFFD88-3277-4D4E-ADD1-FB51353C6C05","userid":"屏柜36","name":"屏柜36","properties":{"所属房间":"房间01","类型":"屏柜"},"position":[-5.7175317004503725,4.01,-5.697643986809803],"model":1,"_temp_belongroom":"房间01"},{"id":"470ECE9C-7C6B-40A4-A21D-6DC9D8571281","userid":"屏柜37","name":"屏柜37","properties":{"所属房间":"房间01","类型":"屏柜"},"position":[128.50446044050673,128.01,-129.70370691938655],"model":1,"_temp_belongroom":"房间01"},{"id":"8DEF774E-3CDA-4A67-A74F-6BBD64B8E6E8","userid":"屏柜38","name":"屏柜38","properties":{"所属房间":"房间01","类型":"屏柜"},"position":[235.72645258146383,233.01,-234.70976985196327],"model":1,"_temp_belongroom":"房间01"},{"id":"70E22646-4AD8-48D7-A169-56417968B3AB","userid":"屏柜39","name":"屏柜39","properties":{"所属房间":"房间01","类型":"屏柜"},"position":[174.94844472242096,170.01,-171.71583278454003],"model":1,"_temp_belongroom":"房间01"},{"id":"44850601-B586-4AAD-9944-DF8011DFEBA4","userid":"屏柜40","name":"屏柜40","properties":{"所属房间":"房间01","类型":"屏柜"},"position":[172.17043686337806,165.01,-166.72189571711675],"model":1,"_temp_belongroom":"房间01"},{"id":"191450E6-CAAB-48B5-96A4-11387DC2C8B3","userid":"屏柜41","name":"屏柜41","properties":{"所属房间":"房间01","类型":"屏柜"},"position":[-190.43043874627364,178.01,190.41569811091543],"model":1,"_temp_belongroom":"房间01"},{"id":"8506323E-7F25-4C08-8152-CF56B78BF082","userid":"屏柜42","name":"屏柜42","properties":{"所属房间":"房间01","类型":"屏柜"},"position":[-141.20844660531654,131.01,143.4096351783387],"model":1,"_temp_belongroom":"房间01"},{"id":"D6D7EBAB-E26A-4557-8436-97BE843D3A2B","userid":"屏柜43","name":"屏柜43","properties":{"所属房间":"房间01","类型":"屏柜"},"position":[-49.98645446435944,42.01,54.40357224576196],"model":1,"_temp_belongroom":"房间01"},{"id":"DA9BF28D-A7B4-48EF-A409-94F03311D186","userid":"屏柜44","name":"屏柜44","properties":{"所属房间":"房间01","类型":"屏柜"},"position":[-140.76446232340234,135.01,147.39750931318522],"model":1,"_temp_belongroom":"房间01"},{"id":"11AA8117-EA15-49C3-A57A-BCC706189C07","userid":"屏柜45","name":"屏柜45","properties":{"所属房间":"房间01","类型":"屏柜"},"position":[-9.542470182445228,6.01,18.391446380608475],"model":1,"_temp_belongroom":"房间01"},{"id":"D682DFBA-07D0-4161-AF79-952C4DD05A6A","userid":"屏柜46","name":"屏柜46","properties":{"所属房间":"房间01","类型":"屏柜"},"position":[-108.32047804148812,107.01,119.38538344803173],"model":1,"_temp_belongroom":"房间01"},{"id":"DEF151F7-1D0E-4C6E-8D10-80FE2371F701","userid":"屏柜47","name":"屏柜47","properties":{"所属房间":"房间01","类型":"屏柜"},"position":[0.901514099468983,0.010000000000000002,12.379320515454996],"model":1,"_temp_belongroom":"房间01"},{"id":"F57627BA-8633-4363-AA07-BE2C81255D8E","userid":"屏柜48","name":"屏柜48","properties":{"所属房间":"房间01","类型":"屏柜"},"position":[146.12350624042608,143.01,155.37325758287824],"model":1,"_temp_belongroom":"房间01"},{"id":"D7F4BC0A-AA38-4204-833F-20EC3DEECEF7","userid":"屏柜49","name":"屏柜49","properties":{"所属房间":"房间01","类型":"屏柜"},"position":[251.3454983813832,246.01,258.3671946503015],"model":1,"_temp_belongroom":"房间01"},{"id":"69326E4A-5A41-44F3-A0FE-CAA990078392","userid":"屏柜50","name":"屏柜50","properties":{"所属房间":"房间01","类型":"屏柜"},"position":[154.5674905223403,147.01,159.3611317177248],"model":1,"_temp_belongroom":"房间01"}]},{"id":"12E321CD-D0FC-44EA-9699-6AAC82866E07","userid":"主楼二层","name":"主楼二层","position":[-13.328815684881562,9,-8.162631965076393],"corners":[[15.226064734728714,0,20.449051150530906],[15.226064734728716,0,18.862851286597287],[15.226064734728716,0,-12.873028621720774],[-20.334275881011685,0,-12.873028635241127],[-20.334275881011685,0,20.449051150530906],[30.8634988014857,0,20.449051159504613],[30.863498801485708,0,-12.873028612747065]],"walls":[{"id":"F9C876FF-F658-4C29-839D-E5373C437680","corners":[5,6],"type":0,"lefttexture":3,"righttexture":3,"edgetexture":4,"blocksize":[3,3],"uvmultiple":[1,1]},{"id":"0085D518-6227-4AE3-95C4-11B0A8751787","corners":[3,4],"type":0,"lefttexture":3,"righttexture":3,"edgetexture":4,"blocksize":[3,3],"uvmultiple":[1,1]},{"id":"D97F6E5B-CF3E-4095-9B07-8A031BA5391B","corners":[6,2],"type":0,"lefttexture":3,"righttexture":3,"edgetexture":4,"blocksize":[3,3],"uvmultiple":[1,1]},{"id":"9618B9D5-0C7E-486B-8827-E81A8FD85836","corners":[2,3],"type":0,"lefttexture":3,"righttexture":3,"edgetexture":4,"blocksize":[3,3],"uvmultiple":[1,1]},{"id":"9B6B0452-B782-4158-82AB-EBCB89111657","corners":[1,2],"type":0,"lefttexture":3,"righttexture":3,"edgetexture":4,"blocksize":[3,3],"uvmultiple":[1,1]},{"id":"22F2DB27-0A1D-4C2B-9335-72869ADF6C60","corners":[4,0],"type":0,"lefttexture":3,"righttexture":3,"edgetexture":4,"blocksize":[3,3],"uvmultiple":[1,1]},{"id":"615995AB-16B6-42C7-BD07-EBD2470399B6","corners":[0,5],"type":0,"lefttexture":3,"righttexture":3,"edgetexture":4,"blocksize":[3,3],"uvmultiple":[1,1]},{"id":"185444A6-32FF-4C67-9025-5B69193E8202","corners":[1,0],"type":0,"lefttexture":3,"righttexture":3,"edgetexture":4,"blocksize":[3,3],"uvmultiple":[1,1]}],"rooms":[{"id":"26888FFF-5D15-4D1D-BB21-4B3C72952898","userid":"房间03","name":"房间03","rooftexture":0,"ceilingtexture":1,"floortexture":2,"roofcustomtexture":0,"ceilingcustomtexture":1,"floorcustomtexture":2,"isshowroof":false,"isshowceiling":false,"corners":[0,1,2,3,4]},{"id":"65ECE9EC-07E5-401A-895F-3372713C8850","rooftexture":0,"ceilingtexture":1,"floortexture":2,"roofcustomtexture":0,"ceilingcustomtexture":1,"floorcustomtexture":2,"corners":[1,0,5,6,2]}],"placements":[{"id":"9B89EE2D-1E67-47D9-A0D5-7A644C55261B","userid":"开光柜01","name":"开光柜01","properties":{"firm":"海德森","unittype":"配电柜1","loadbearing":"900","power":"1000","version":"1.0","devicetype":"独立设备","tags":"[\"配电柜\"]","类型":"开光柜","所属房间":"房间03"},"position":[-38.50382305917668,26.009999999999998,34.837759245092684],"model":2,"_temp_belongroom":"房间03"},{"id":"278D16E0-6502-4F04-9167-270CC7B39CEC","userid":"开光柜02","name":"开光柜02","properties":{"firm":"海德森","unittype":"配电柜1","loadbearing":"900","power":"1000","version":"1.0","devicetype":"独立设备","tags":"[\"配电柜\"]","类型":"开光柜","所属房间":"房间03"},"position":[-246.5038274142384,237.01,245.83775924509268],"model":2,"_temp_belongroom":"房间03"},{"id":"EE2004D6-BBD1-4281-B1D4-670F59997F22","userid":"开光柜03","name":"开光柜03","properties":{"firm":"海德森","unittype":"配电柜1","loadbearing":"900","power":"1000","version":"1.0","devicetype":"独立设备","tags":"[\"配电柜\"]","类型":"开光柜","所属房间":"房间03"},"position":[-41.5038317693001,35.01,43.837759245092684],"model":2,"_temp_belongroom":"房间03"},{"id":"2C0EF6E1-4351-412A-9AEF-E74625E0B67F","userid":"开光柜04","name":"开光柜04","properties":{"firm":"海德森","unittype":"配电柜1","loadbearing":"900","power":"1000","version":"1.0","devicetype":"独立设备","tags":"[\"配电柜\"]","类型":"开光柜","所属房间":"房间03"},"position":[-129.5038361243618,126.01,134.83775924509268],"model":2,"_temp_belongroom":"房间03"},{"id":"A2487762-0234-4204-BA4C-C67B8FAE3D38","userid":"开光柜05","name":"开光柜05","properties":{"firm":"海德森","unittype":"配电柜1","loadbearing":"900","power":"1000","version":"1.0","devicetype":"独立设备","tags":"[\"配电柜\"]","类型":"开光柜","所属房间":"房间03"},"position":[-57.503840479423516,57.01,65.83775924509268],"model":2,"_temp_belongroom":"房间03"},{"id":"361BA576-E28A-460C-8F5C-8086344E3C90","userid":"开光柜06","name":"开光柜06","properties":{"firm":"海德森","unittype":"配电柜1","loadbearing":"900","power":"1000","version":"1.0","devicetype":"独立设备","tags":"[\"配电柜\"]","类型":"开光柜","所属房间":"房间03"},"position":[147.49615516551478,145.01,153.83775924509268],"model":2,"_temp_belongroom":"房间03"},{"id":"009C79A8-465E-427E-BE2F-5649A5E17EE4","userid":"开光柜07","name":"开光柜07","properties":{"firm":"海德森","unittype":"配电柜1","loadbearing":"900","power":"1000","version":"1.0","devicetype":"独立设备","tags":"[\"配电柜\"]","类型":"开光柜","所属房间":"房间03"},"position":[234.49615081045306,229.01,237.83775924509268],"model":2,"_temp_belongroom":"房间03"},{"id":"79CE0446-5A10-4FBD-9E98-1BD4C50B828A","userid":"开光柜08","name":"开光柜08","properties":{"firm":"海德森","unittype":"配电柜1","loadbearing":"900","power":"1000","version":"1.0","devicetype":"独立设备","tags":"[\"配电柜\"]","类型":"开光柜","所属房间":"房间03"},"position":[-151.50382305917668,139.01,143.1971306169646],"model":2,"_temp_belongroom":"房间03"},{"id":"E9016FD8-C464-4F7E-A017-3676BAC8B155","userid":"开光柜09","name":"开光柜09","properties":{"firm":"海德森","unittype":"配电柜1","loadbearing":"900","power":"1000","version":"1.0","devicetype":"独立设备","tags":"[\"配电柜\"]","类型":"开光柜","所属房间":"房间03"},"position":[-93.50382741423839,84.01,88.19713061696461],"model":2,"_temp_belongroom":"房间03"},{"id":"CEE8A280-A4D4-4AE6-95D2-EC0C526CE9C3","userid":"开光柜10","name":"开光柜10","properties":{"firm":"海德森","unittype":"配电柜1","loadbearing":"900","power":"1000","version":"1.0","devicetype":"独立设备","tags":"[\"配电柜\"]","类型":"开光柜","所属房间":"房间03"},"position":[-200.5038317693001,194.01,198.1971306169646],"model":2,"_temp_belongroom":"房间03"},{"id":"B9268980-1A1F-494F-AC71-8419AFF3998E","userid":"开光柜11","name":"开光柜11","properties":{"firm":"海德森","unittype":"配电柜1","loadbearing":"900","power":"1000","version":"1.0","devicetype":"独立设备","tags":"[\"配电柜\"]","类型":"开光柜","所属房间":"房间03"},"position":[-146.5038361243618,143.01,147.1971306169646],"model":2,"_temp_belongroom":"房间03"},{"id":"6D3A5DBB-B551-4D65-8411-C55C130EF433","userid":"开光柜12","name":"开光柜12","properties":{"firm":"海德森","unittype":"配电柜1","loadbearing":"900","power":"1000","version":"1.0","devicetype":"独立设备","tags":"[\"配电柜\"]","类型":"开光柜","所属房间":"房间03"},"position":[-50.503840479423516,50.01,54.197130616964614],"model":2,"_temp_belongroom":"房间03"},{"id":"F238A698-BB92-45D1-B3A2-B070EEBB6556","userid":"开光柜13","name":"开光柜13","properties":{"firm":"海德森","unittype":"配电柜1","loadbearing":"900","power":"1000","version":"1.0","devicetype":"独立设备","tags":"[\"配电柜\"]","类型":"开光柜","所属房间":"房间03"},"position":[89.49615516551478,87.01,91.19713061696461],"model":2,"_temp_belongroom":"房间03"},{"id":"3BC4CC73-0871-49E0-84AB-231130F64DE9","userid":"开光柜14","name":"开光柜14","properties":{"firm":"海德森","unittype":"配电柜1","loadbearing":"900","power":"1000","version":"1.0","devicetype":"独立设备","tags":"[\"配电柜\"]","类型":"开光柜","所属房间":"房间03"},"position":[237.49615081045306,232.01,236.1971306169646],"model":2,"_temp_belongroom":"房间03"},{"id":"73199F6E-28FF-4BA9-A619-3C743A3662C0","userid":"开光柜15","name":"开光柜15","properties":{"firm":"海德森","unittype":"配电柜1","loadbearing":"900","power":"1000","version":"1.0","devicetype":"独立设备","tags":"[\"配电柜\"]","类型":"开光柜","所属房间":"房间03"},"position":[198.49615081045306,193.01,205.61655812485304],"model":2,"_temp_belongroom":"房间03"},{"id":"1E922764-CE55-4675-A3D5-06A306F17E55","userid":"开光柜16","name":"开光柜16","properties":{"firm":"海德森","unittype":"配电柜1","loadbearing":"900","power":"1000","version":"1.0","devicetype":"独立设备","tags":"[\"配电柜\"]","类型":"开光柜","所属房间":"房间03"},"position":[86.49615516551478,84.01,96.61655812485306],"model":2,"_temp_belongroom":"房间03"},{"id":"6E30E528-0408-490D-A795-DEF17C2E01C2","userid":"开光柜17","name":"开光柜17","properties":{"firm":"海德森","unittype":"配电柜1","loadbearing":"900","power":"1000","version":"1.0","devicetype":"独立设备","tags":"[\"配电柜\"]","类型":"开光柜","所属房间":"房间03"},"position":[-195.5038404794235,195.01,207.61655812485304],"model":2,"_temp_belongroom":"房间03"},{"id":"0F02E643-9F5B-4523-B244-6059A680D729","userid":"开光柜18","name":"开光柜18","properties":{"firm":"海德森","unittype":"配电柜1","loadbearing":"900","power":"1000","version":"1.0","devicetype":"独立设备","tags":"[\"配电柜\"]","类型":"开光柜","所属房间":"房间03"},"position":[-43.50383612436181,40.01,52.61655812485306],"model":2,"_temp_belongroom":"房间03"},{"id":"6A93BB7E-15DB-4B97-996E-44E472C06A4A","userid":"开光柜19","name":"开光柜19","properties":{"firm":"海德森","unittype":"配电柜1","loadbearing":"900","power":"1000","version":"1.0","devicetype":"独立设备","tags":"[\"配电柜\"]","类型":"开光柜","所属房间":"房间03"},"position":[-81.50383176930009,75.01,87.61655812485306],"model":2,"_temp_belongroom":"房间03"},{"id":"D72EE9DA-37CD-46B6-8D1A-B70A15A5E036","userid":"开光柜20","name":"开光柜20","properties":{"firm":"海德森","unittype":"配电柜1","loadbearing":"900","power":"1000","version":"1.0","devicetype":"独立设备","tags":"[\"配电柜\"]","类型":"开光柜","所属房间":"房间03"},"position":[-64.50382741423839,55.01,67.61655812485306],"model":2,"_temp_belongroom":"房间03"},{"id":"31A707F6-A050-433C-9A6C-B087146239B1","userid":"开光柜21","name":"开光柜21","properties":{"firm":"海德森","unittype":"配电柜1","loadbearing":"900","power":"1000","version":"1.0","devicetype":"独立设备","tags":"[\"配电柜\"]","类型":"开光柜","所属房间":"房间03"},"position":[-188.50382305917668,176.01,188.61655812485304],"model":2,"_temp_belongroom":"房间03"}]},{"id":"4D9417EC-75A0-4863-8E3F-D7483BB88536","userid":"主楼三层","name":"主楼三层","position":[-62.32881568488156,61,-57.16263196507639],"corners":[[64.22606473472871,0,69.4490511505309],[64.22606473472871,0,67.86285128659729],[64.22606473472871,0,-61.87302862172078],[-69.33427588101169,0,-61.87302863524113],[-69.33427588101168,0,69.4490511505309],[79.8634988014857,0,69.44905115950462],[79.8634988014857,0,-61.87302861274706]],"walls":[{"id":"6A978DAB-371A-4CD2-BF47-43A63A643369","corners":[5,6],"type":0,"lefttexture":3,"righttexture":3,"edgetexture":4,"blocksize":[3,3],"uvmultiple":[1,1]},{"id":"F4C0B7BD-7F81-432F-9C5E-A4BC4C9F7135","corners":[3,4],"type":0,"lefttexture":3,"righttexture":3,"edgetexture":4,"blocksize":[3,3],"uvmultiple":[1,1]},{"id":"BCA9F3A0-B9AB-4209-A1BD-C95979C34AED","corners":[6,2],"type":0,"lefttexture":3,"righttexture":3,"edgetexture":4,"blocksize":[3,3],"uvmultiple":[1,1]},{"id":"707519B6-1F60-4707-857F-F6727668944E","corners":[2,3],"type":0,"lefttexture":3,"righttexture":3,"edgetexture":4,"blocksize":[3,3],"uvmultiple":[1,1]},{"id":"97084582-A068-4F1F-8BED-7D782785C9F3","corners":[1,2],"type":0,"lefttexture":3,"righttexture":3,"edgetexture":4,"blocksize":[3,3],"uvmultiple":[1,1]},{"id":"7E55DD8B-6BA9-41C6-98E9-89A1E205C196","corners":[4,0],"type":0,"lefttexture":3,"righttexture":3,"edgetexture":4,"blocksize":[3,3],"uvmultiple":[1,1]},{"id":"5C1C5465-5FF8-43F4-8CDB-6237E82AA5B7","corners":[0,5],"type":0,"lefttexture":3,"righttexture":3,"edgetexture":4,"blocksize":[3,3],"uvmultiple":[1,1]},{"id":"E544E2E5-0A26-4E79-81D7-9837BD580610","corners":[1,0],"type":0,"lefttexture":3,"righttexture":3,"edgetexture":4,"blocksize":[3,3],"uvmultiple":[1,1]}],"rooms":[{"id":"9B412136-2CB4-4395-86D1-AA00160B211E","name":"房间01","rooftexture":0,"ceilingtexture":1,"floortexture":2,"roofcustomtexture":0,"ceilingcustomtexture":1,"floorcustomtexture":2,"isshowroof":false,"isshowceiling":false,"corners":[0,1,2,3,4]},{"id":"439C9BB6-EAC8-4628-BD20-FEE1646673FB","rooftexture":0,"ceilingtexture":1,"floortexture":2,"roofcustomtexture":0,"ceilingcustomtexture":1,"floorcustomtexture":2,"corners":[1,0,5,6,2]}]},{"id":"DDB467B5-3BD1-4D91-A92B-1BD156B4846B","userid":"主楼四层","name":"主楼四层","position":[-113.32881568488156,115,-108.1626319650764],"corners":[[115.22606473472871,0,120.4490511505309],[115.22606473472871,0,118.86285128659729],[115.22606473472871,0,-112.87302862172078],[-120.33427588101169,0,-112.87302863524113],[-120.33427588101168,0,120.4490511505309],[130.8634988014857,0,120.44905115950462],[130.86349880148572,0,-112.87302861274706]],"walls":[{"id":"B72EAD6A-FAB8-4D8E-8EE3-B543C0C044AD","corners":[5,6],"type":0,"lefttexture":3,"righttexture":3,"edgetexture":4,"blocksize":[3,3],"uvmultiple":[1,1]},{"id":"2144E8BE-E903-486D-A7AA-86C7A05C42FA","corners":[3,4],"type":0,"lefttexture":3,"righttexture":3,"edgetexture":4,"blocksize":[3,3],"uvmultiple":[1,1]},{"id":"B307C8F2-AA92-4E03-BF13-20F1E2041D83","corners":[6,2],"type":0,"lefttexture":3,"righttexture":3,"edgetexture":4,"blocksize":[3,3],"uvmultiple":[1,1]},{"id":"2D302770-D129-41FE-B2A8-089778E62A55","corners":[2,3],"type":0,"lefttexture":3,"righttexture":3,"edgetexture":4,"blocksize":[3,3],"uvmultiple":[1,1]},{"id":"BF8FD92D-D36F-49DC-9FD1-915E5EA684AD","corners":[1,2],"type":0,"lefttexture":3,"righttexture":3,"edgetexture":4,"blocksize":[3,3],"uvmultiple":[1,1]},{"id":"32821FC2-90FD-4E39-ABE4-0EED69CFE060","corners":[4,0],"type":0,"lefttexture":3,"righttexture":3,"edgetexture":4,"blocksize":[3,3],"uvmultiple":[1,1]},{"id":"B4C47244-99BD-4852-9979-529AA5068B9B","corners":[0,5],"type":0,"lefttexture":3,"righttexture":3,"edgetexture":4,"blocksize":[3,3],"uvmultiple":[1,1]},{"id":"B81488C6-91FC-4E37-8B49-0CE2EAE660A0","corners":[1,0],"type":0,"lefttexture":3,"righttexture":3,"edgetexture":4,"blocksize":[3,3],"uvmultiple":[1,1]}],"rooms":[{"id":"877C3E6B-2761-4B49-92F6-B56BEBCE7154","name":"房间01","rooftexture":0,"ceilingtexture":1,"floortexture":2,"roofcustomtexture":0,"ceilingcustomtexture":1,"floorcustomtexture":2,"isshowroof":false,"isshowceiling":false,"corners":[0,1,2,3,4]},{"id":"517C026A-FA1B-4789-B504-59D865CF44E2","rooftexture":0,"ceilingtexture":1,"floortexture":2,"roofcustomtexture":0,"ceilingcustomtexture":1,"floorcustomtexture":2,"corners":[1,0,5,6,2]}]}],"facades":[{"id":"1B10DABB-56E3-4899-B7BE-9F39DEB6E3CF","properties":{"_styleTag_":"FacadeMain"},"position":[0,0,0],"model":0}]}],"outdoors":{"id":"1","name":"新楼层","corners":[[-71.91515220102006,0,-52.03489000418287],[-71.91515220102006,0,32.45227560596966],[62.66436651462173,0,32.45227560596966],[62.66436651462173,0,-52.03489000418287]],"walls":[{"id":"667D7ACC-A01F-4A30-B778-F08098949AFC","corners":[1,2],"type":1,"model":3,"thick":0.65,"height":0.64584},{"id":"8EE7D5EE-521F-41EE-BDE6-955EA654E4E3","corners":[2,3],"type":1,"model":3,"thick":0.65,"height":0.64584},{"id":"A8E6450D-66FA-418D-9160-9EC91C0FCFCA","corners":[3,0],"type":1,"model":3,"thick":0.65,"height":0.64584},{"id":"579E78E9-629A-4836-ACDC-FA894638439C","corners":[0,1],"type":1,"model":3,"thick":0.65,"height":0.64584}],"rooms":[{"id":"42D71824-A720-45BD-9A36-15F479C7A7F4","rooftexture":0,"ceilingtexture":1,"floortexture":5,"roofcustomtexture":0,"ceilingcustomtexture":1,"floorcustomtexture":5,"isshowroof":false,"isshowceiling":false,"corners":[0,1,2,3]}],"placements":[{"id":"C813E267-FB37-47ED-BA53-C037754E89E1","properties":{"_styleTag_":"Facade"},"position":[247.17284498272426,224.01,-253.76797058030957],"model":4},{"id":"D3E7A2F4-B51D-4389-8020-C81D26848087","properties":{"_styleTag_":"Objects"},"position":[-158.04479677618323,134.01,162.09738019392478],"model":5},{"id":"DA5C7086-BF4D-4982-87BB-88E02B3903F4","properties":{"_styleTag_":"Objects"},"position":[-260.61196544129945,245.01,273.1000711156731],"model":5},{"id":"ADA3CEE8-8C21-4A17-923D-441623522A10","properties":{"_styleTag_":"Objects"},"position":[-24.179134106415624,17.009999999999987,45.102762037421414],"model":5},{"id":"EC022F33-AF5C-4F99-977B-0D26A82255EB","properties":{"_styleTag_":"Objects"},"position":[235.25369722846818,234.01,262.1054529591697],"model":5},{"id":"BCA9D5E2-3D3A-4715-8137-CA175B2F00AC","properties":{"_styleTag_":"Objects"},"position":[182.686528563352,173.01,201.10814388091805],"model":5},{"id":"DD42773A-E4E4-43A7-AF3F-8F2A802A5BCD","properties":{"_styleTag_":"Objects"},"position":[222.11935989823579,204.01,232.11083480266637],"model":5},{"id":"6CF4DE0E-EC1C-42CE-8E41-6388AA250793","properties":{"_styleTag_":"Objects"},"position":[172.5521912331196,146.01,174.11352572441467],"model":5},{"id":"5B9602D3-9603-486E-A1F3-5A4D5774E50F","properties":{"_styleTag_":"Objects"},"position":[48.9850225680034,14.009999999999986,42.116216646163004],"model":5},{"id":"AD6989CF-B2D9-492A-A6DD-E316DE4522D3","properties":{"_styleTag_":"Objects"},"position":[253.4178539028872,210.01,238.11890756791132],"model":5},{"id":"4B87D773-02FB-4561-BCF7-D0AC07F3C94E","properties":{"_styleTag_":"Objects"},"position":[130.85068523777102,79.00999999999999,107.12159848965963],"model":5},{"id":"7CFDE7A7-87E7-4D06-8738-EBA2C1890945","properties":{"_styleTag_":"Objects"},"position":[-132.6028598064261,68.01,-115.89722441437031],"model":6},{"id":"D03BDDF4-5D87-4505-8466-039331EF6D0E","properties":{"_styleTag_":"Objects"},"position":[-70.74793702568797,15.01,-62.99261454589896],"model":6},{"id":"8D98CFCE-3CD9-4753-BF0E-31FDCFF54949","properties":{"_styleTag_":"Objects"},"position":[-118.89301424494987,72.01,-120.0880046774276],"model":6},{"id":"C2B5DAAE-F8A7-455A-999C-4AF9E178D7D2","properties":{"_styleTag_":"Objects"},"position":[-249.03809146421176,211.01,-259.1833948089563],"model":6},{"id":"A88565B4-90FA-484B-8302-E9FDAFBA61EE","properties":{"_styleTag_":"Objects"},"position":[-268.18316868347364,239.01,-287.2787849404849],"model":6},{"id":"00307D9C-86A3-4A4C-BA57-226D4933CC84","properties":{"_styleTag_":"Objects"},"position":[-144.47332312199742,133.01,-181.4695652035422],"model":6},{"id":"F0A4982E-70B8-45BE-AA05-B545C0DB881B","userid":"消防栓01","name":"消防栓01","position":[-90.44504496599826,26.01,31.690879543453235],"model":7},{"id":"892A7720-2939-4942-95E0-63699B324365","userid":"消防栓02","name":"消防栓02","position":[-119.16572348638492,100.01,105.42211684458118],"model":7},{"id":"B69BCAE2-686F-4B29-9AE7-9266E834463B","userid":"消防栓03","name":"消防栓03","position":[-68.73289215150109,58.01,-70.007431545801],"model":7},{"id":"BF9566B2-2E39-489D-A116-631F09D56306","userid":"消防栓04","name":"消防栓04","position":[-17.732892151501098,7.01,-45.39704672005381],"model":7}]}}